waldur_client/__init__.py
python_waldur_client-0.6.4.dist-info/LICENSE.md
python_waldur_client-0.6.4.dist-info/METADATA
python_waldur_client-0.6.4.dist-info/WHEEL
python_waldur_client-0.6.4.dist-info/RECORD
