Metadata-Version: 2.3
Name: python-waldur-client
Version: 0.6.4
Summary: REST client for the Waldur API.
License: MIT
Author: OpenNode Team
Author-email: info@opennodecloud.com
Requires-Python: >=3.8
Classifier: Intended Audience :: Developers
Classifier: License :: OSI Approved :: MIT License
Classifier: Operating System :: OS Independent
Classifier: Programming Language :: Python :: 3
Classifier: Programming Language :: Python :: 3.8
Classifier: Programming Language :: Python :: 3.9
Classifier: Programming Language :: Python :: 3.10
Classifier: Programming Language :: Python :: 3.11
Classifier: Programming Language :: Python :: 3.12
Classifier: Programming Language :: Python :: 3.13
Requires-Dist: requests (>=2.6.0)
Requires-Dist: typing-extensions (>=4.12.2,<5.0.0)
Project-URL: Homepage, https://waldur.com
